modulift/__init__.py
modulift/api.py
modulift/data.py
modulift/funcs.py
modulift-0.1.0.dist-info/METADATA
modulift-0.1.0.dist-info/WHEEL
modulift-0.1.0.dist-info/top_level.txt
modulift-0.1.0.dist-info/RECORD
