Metadata-Version: 2.1
Name: modulift
Version: 0.1.0
Summary: A powerful search tool for discovering Python packages based on user queries
Home-page: https://github.com/okanyenigun/modulift
Author: Okan Yenigün
Author-email: okanyenigun@gmail.com
License: MIT
Classifier: Development Status :: 3 - Alpha
Classifier: Intended Audience :: Developers
Classifier: Intended Audience :: Science/Research
Classifier: Intended Audience :: Information Technology
Classifier: Intended Audience :: Education
Classifier: Topic :: Software Development :: Libraries :: Python Modules
Classifier: Topic :: Software Development :: Documentation
Classifier: Topic :: Scientific/Engineering :: Information Analysis
Classifier: License :: OSI Approved :: MIT License
Classifier: Programming Language :: Python :: 3
Classifier: Programming Language :: Python :: 3.7
Classifier: Programming Language :: Python :: 3.8
Classifier: Programming Language :: Python :: 3.9
Classifier: Programming Language :: Python :: 3.10
Classifier: Programming Language :: Python :: 3.11
Classifier: Operating System :: OS Independent
Requires-Python: >=3.7
Requires-Dist: datasets==3.1.0
Requires-Dist: scikit-learn==1.6.1
Requires-Dist: ipywidgets==8.1.5
Requires-Dist: sentence-transformers==3.4.1
Provides-Extra: dev
Requires-Dist: twine==5.1.1; extra == "dev"
Provides-Extra: test
Requires-Dist: pytest==8.2.2; extra == "test"
